cpskin.demo-1.0a1-py2.7-nspkg.pth
cpskin/demo/__init__.py
cpskin/demo/configure.zcml
cpskin/demo/interfaces.py
cpskin/demo/setuphandlers.py
cpskin/demo/testing.py
cpskin/demo/browser/__init__.py
cpskin/demo/browser/configure.zcml
cpskin/demo/browser/overrides/.gitkeep
cpskin/demo/browser/static/.gitkeep
cpskin/demo/data/atelierphoto.jpg
cpskin/demo/data/brasserie.jpg
cpskin/demo/data/concert.jpg
cpskin/demo/data/marcheauxfleurs.jpg
cpskin/demo/data/meteo.jpg
cpskin/demo/data/moto.jpg
cpskin/demo/locales/cpskin.demo.pot
cpskin/demo/locales/update.sh
cpskin/demo/profiles/default/browserlayer.xml
cpskin/demo/profiles/default/cpskindemo_default.txt
cpskin/demo/profiles/default/metadata.xml
cpskin/demo/tests/__init__.py
cpskin/demo/tests/test_robot.py
cpskin/demo/tests/test_setup.py
cpskin/demo/tests/robot/test_example.robot
cpskin.demo-1.0a1.dist-info/DESCRIPTION.rst
cpskin.demo-1.0a1.dist-info/METADATA
cpskin.demo-1.0a1.dist-info/RECORD
cpskin.demo-1.0a1.dist-info/WHEEL
cpskin.demo-1.0a1.dist-info/entry_points.txt
cpskin.demo-1.0a1.dist-info/metadata.json
cpskin.demo-1.0a1.dist-info/namespace_packages.txt
cpskin.demo-1.0a1.dist-info/top_level.txt
