Metadata-Version: 2.0
Name: cpskin.demo
Version: 1.0a1
Summary: Demo profile for cpskin suite
Home-page: https://pypi.python.org/pypi/cpskin.demo
Author: Benoit Suttor
Author-email: bsuttor@imio.be
License: GPL version 2
Keywords: Python Plone
Platform: UNKNOWN
Classifier: Environment :: Web Environment
Classifier: Framework :: Plone
Classifier: Framework :: Plone :: 4.3
Classifier: Programming Language :: Python
Classifier: Programming Language :: Python :: 2.7
Classifier: Operating System :: OS Independent
Classifier: License :: OSI Approved :: GNU General Public License v2 (GPLv2)
Provides-Extra: test
Requires-Dist: plone.api
Requires-Dist: setuptools
Requires-Dist: cpskin.policy
Requires-Dist: collective.plonetruegallery
Requires-Dist: imio.helpers
Provides-Extra: test
Requires-Dist: plone.app.testing; extra == 'test'
Requires-Dist: plone.app.contenttypes; extra == 'test'
Requires-Dist: plone.app.robotframework[debug]; extra == 'test'
